KafkaMetricsExporter/__init__.py
KafkaMetricsExporter-0.0.3.dist-info/METADATA
KafkaMetricsExporter-0.0.3.dist-info/WHEEL
KafkaMetricsExporter-0.0.3.dist-info/top_level.txt
KafkaMetricsExporter-0.0.3.dist-info/RECORD
